cvpy/__init__.py
cvpy/cvw/__init__.py
cvpy/cvw/_cv2_wrapper.py
cvpy/cvw/viewer/__init__.py
cvpy/cvw/viewer/_image_key_binder.py
cvpy/imseg/__init__.py
cvpy/imseg/_utils.py
cvpy/imseg/bbox.py
cvpy/imseg/contour.py
cvpy/imseg/immasks/__init__.py
cvpy/imseg/immasks/_utils.py
cvpy/imseg/immasks/mask_utils.py
cvpy/imseg/immasks/masks.py
cvpy_toolkit-0.1.0.dist-info/METADATA
cvpy_toolkit-0.1.0.dist-info/WHEEL
cvpy_toolkit-0.1.0.dist-info/licenses/LICENSE
cvpy_toolkit-0.1.0.dist-info/RECORD
