Metadata-Version: 2.3
Name: cvpy-toolkit
Version: 0.1.0
Summary: Add your description here
Author-email: joshfisher <joshfisher81@gmail.com>
License-File: LICENSE
Requires-Python: >=3.11
Requires-Dist: build>=1.2.2
Requires-Dist: numpy>=2.1.0
Requires-Dist: opencv-python>=4.10.0.84
Requires-Dist: pandas>=2.2.2
Requires-Dist: pdoc>=14.6.1
Requires-Dist: twine>=5.1.1
